LICENSE.txt
MANIFEST.in
README.rst
requirements.txt
setup.py
coop_tag/__init__.py
coop_tag/admin.py
coop_tag/forms.py
coop_tag/managers.py
coop_tag/models.py
coop_tag/settings.py
coop_tag/tests.pyc
coop_tag/urls.py
coop_tag/utils.py
coop_tag/views.py
coop_tag/widgets.py
coop_tag.egg-info/PKG-INFO
coop_tag.egg-info/SOURCES.txt
coop_tag.egg-info/dependency_links.txt
coop_tag.egg-info/not-zip-safe
coop_tag.egg-info/top_level.txt
coop_tag/locale/fr/LC_MESSAGES/django.mo
coop_tag/locale/fr/LC_MESSAGES/django.po
coop_tag/migrations/0001_initial.py
coop_tag/migrations/0002_auto__add_tagcategory__add_field_ctag_category.py
coop_tag/migrations/0003_auto__add_field_tagcategory_slug.py
coop_tag/migrations/0004_auto__add_field_tagcategory_position.py
coop_tag/migrations/0005_auto__add_field_ctag_concept_uri__chg_field_tagcategory_slug.py
coop_tag/migrations/0006_auto__add_field_ctag_status__add_field_ctag_uuid__chg_field_ctag_uri.py
coop_tag/migrations/0007_auto__del_field_ctag_author_uri__add_field_ctag_person_uri.py
coop_tag/migrations/0008_auto__chg_field_ctag_created__chg_field_ctag_modified.py
coop_tag/migrations/__init__.py
coop_tag/static/feincms/css/tag_tree.css
coop_tag/static/tagger/css/autoSuggest-grappelli.css
coop_tag/static/tagger/css/autoSuggest.css
coop_tag/static/tagger/css/coop_tag.css
coop_tag/static/tagger/js/autocolumn.js
coop_tag/static/tagger/js/groupbox.js
coop_tag/static/tagger/js/jquery.autoSuggest.minified.js
coop_tag/static/tagger/js/jquery.easyListSplitter.js
coop_tag/templates/admin/feincms/tag_tree_editor.html
coop_tag/templates/tag/tag_detail.html
coop_tag/templates/tag/tagcloud_include.html
coop_tag/templates/tag/taglist_include.html
coop_tag/templatetags/__init__.py
coop_tag/templatetags/tagger_extras.py