Metadata-Version: 1.0
Name: coop-tag
Version: 0.2.1
Summary: Repackaging django-taggit with add-ons
Home-page: https://github.com/quinode/coop-tag/
Author: Cooperative Quinode
Author-email: contact@quinode.fr
License: BSD
Download-URL: https://github.com/quinode/coop-tag/tarball/master
Platform: UNKNOWN
Classifier: Development Status :: 4 - Beta
Classifier: Environment :: Web Environment
Classifier: Intended Audience :: Developers
Classifier: License :: OSI Approved :: BSD License
Classifier: Operating System :: OS Independent
Classifier: Programming Language :: Python
Classifier: Framework :: Django
Classifier: Natural Language :: English
Classifier: Natural Language :: French
Classifier: Topic :: Internet :: WWW/HTTP :: Dynamic Content
Classifier: Topic :: Internet :: WWW/HTTP :: WSGI :: Application
